asrpro/__init__.py
asrpro/__main__.py
asrpro/cli.py
asrpro/processor.py
asrpro-0.2.1.dist-info/METADATA
asrpro-0.2.1.dist-info/WHEEL
asrpro-0.2.1.dist-info/entry_points.txt
asrpro-0.2.1.dist-info/top_level.txt
asrpro-0.2.1.dist-info/RECORD
