Metadata-Version: 2.4
Name: asrpro
Version: 0.2.1
Summary: ASR Audio Preprocessor - Optimize audio files for child speech recognition
Home-page: https://github.com/ss-sebastian/asrpro
Author: Chuqiao 'Sebastian' Song
Author-email: songchuqiao23@gmail.com
Classifier: Programming Language :: Python :: 3
Classifier: License :: OSI Approved :: MIT License
Classifier: Operating System :: OS Independent
Requires-Python: >=3.6
Requires-Dist: pydub>=0.25.1
Requires-Dist: ffmpeg-python>=0.2.0
Dynamic: author
Dynamic: author-email
Dynamic: classifier
Dynamic: description
Dynamic: description-content-type
Dynamic: home-page
Dynamic: requires-dist
Dynamic: requires-python
Dynamic: summary
